opticl/__init__.py
opticl/constraint_learning.py
opticl/embed_mip.py
opticl/embed_mip_gurobi.py
opticl/run_MLmodels.py
opticl-0.0.1.dist-info/LICENSE
opticl-0.0.1.dist-info/METADATA
opticl-0.0.1.dist-info/WHEEL
opticl-0.0.1.dist-info/top_level.txt
opticl-0.0.1.dist-info/RECORD
