Metadata-Version: 2.1
Name: opticl
Version: 0.0.1
Summary: Mixed-integer optimization with constraint learning
Home-page: https://github.com/hwiberg/OptiCL
Classifier: Programming Language :: Python :: 3
Classifier: License :: OSI Approved :: MIT License
Requires-Python: >=3.7
License-File: LICENSE
Requires-Dist: pandas
Requires-Dist: scikit-learn
Requires-Dist: pyomo
Requires-Dist: matplotlib
Requires-Dist: openpyxl
